ssu_package_deploy_tutorial/__init__.py
ssu_package_deploy_tutorial/__main__.py
ssu_package_deploy_tutorial-1.0.0.dist-info/METADATA
ssu_package_deploy_tutorial-1.0.0.dist-info/WHEEL
ssu_package_deploy_tutorial-1.0.0.dist-info/license
ssu_package_deploy_tutorial-1.0.0.dist-info/top_level.txt
ssu_package_deploy_tutorial-1.0.0.dist-info/RECORD
